README.md
setup.cfg
setup.py
vape_clients/__init__.py
vape_clients/ping.py
vape_clients.egg-info/PKG-INFO
vape_clients.egg-info/SOURCES.txt
vape_clients.egg-info/dependency_links.txt
vape_clients.egg-info/top_level.txt